sphericalpolygon/__init__.py
sphericalpolygon/centroid.py
sphericalpolygon/excess_area.py
sphericalpolygon/functions.py
sphericalpolygon/inertia.py
sphericalpolygon/inside_polygon.py
sphericalpolygon/math.py
sphericalpolygon/perimeter.py
sphericalpolygon/polygonclasses/__init__.py
sphericalpolygon/polygonclasses/sphericalpolygon.py
sphericalpolygon-1.2.3.dist-info/licenses/LICENSE.txt
sphericalpolygon-1.2.3.dist-info/METADATA
sphericalpolygon-1.2.3.dist-info/WHEEL
sphericalpolygon-1.2.3.dist-info/top_level.txt
sphericalpolygon-1.2.3.dist-info/RECORD
