Metadata-Version: 2.4
Name: sphericalpolygon
Version: 1.2.3
Summary: A package to handle the spherical polygon
Home-page: https://github.com/lcx366/SphericalPolygon
Author: Chunxiao Li
Author-email: lcx366@126.com
License: MIT
Keywords: spherical polygon,polygon area,polygon inertia tensor
Classifier: Development Status :: 4 - Beta
Classifier: Intended Audience :: Education
Classifier: Intended Audience :: Science/Research
Classifier: Programming Language :: Python :: 3.11
Classifier: Programming Language :: Python :: 3.12
Classifier: Programming Language :: Python :: 3.13
Classifier: License :: OSI Approved :: MIT License
Requires-Python: >=3.11
License-File: LICENSE.txt
Requires-Dist: scipy
Requires-Dist: numpy
Dynamic: author
Dynamic: author-email
Dynamic: classifier
Dynamic: description
Dynamic: description-content-type
Dynamic: home-page
Dynamic: keywords
Dynamic: license
Dynamic: license-file
Dynamic: requires-dist
Dynamic: requires-python
Dynamic: summary
